{
  "candidatos": [
    {
      "nome": "diegoigor2001@gmail.com",
      "email": "diegoigor2001@gmail.com",
      "dataEntrevista": "",
      "numero1": "",
      "numero2": "",
      "pais": "Brasil",
      "estado": "PE",
      "cidade": "Recife",
      "bairro": "",
      "nivel": "",
      "nascimento": "",
      "pretencao": "",
      "vaga": "",
      "descri": "",
      "sql": "",
      "lg": "",
      "en": "",
      "id": 1
    },
    {
      "nomeVaga": "teste",
      "localidade": "",
      "tempoAlocacao": "",
      "descricaoVaga": "",
      "idioma": "",
      "skillTecnica": "",
      "id": 2
    },
    {
      "nome": "candidato",
      "email": "",
      "dataEntrevista": "",
      "numero1": "",
      "numero2": "",
      "pais": "",
      "estado": "",
      "cidade": "",
      "bairro": "",
      "nivel": "",
      "nascimento": "",
      "pretencao": "",
      "vaga": "",
      "descri": "",
      "sql": "",
      "lg": "",
      "en": "",
      "id": 3
    },
    {
      "nomeVaga": "vagas",
      "localidade": "",
      "tempoAlocacao": "",
      "descricaoVaga": "",
      "idioma": "",
      "skillTecnica": "",
      "id": 4
    }
  ],
  "vagas": [
    {
      "nomeVaga": "teste",
      "localidade": "Recife",
      "tempoAlocacao": "2022-11-12",
      "descricaoVaga": "",
      "idioma": "",
      "skillTecnica": "",
      "id": 1
    }
  ]
}